setup.py
ovos_test_ocp_audio_plugin/__init__.py
ovos_test_ocp_audio_plugin.egg-info/PKG-INFO
ovos_test_ocp_audio_plugin.egg-info/SOURCES.txt
ovos_test_ocp_audio_plugin.egg-info/dependency_links.txt
ovos_test_ocp_audio_plugin.egg-info/entry_points.txt
ovos_test_ocp_audio_plugin.egg-info/top_level.txt